{
    "banners": {
        "103": {
            "title": "滿月紅利",
            "image": "http://dy0t2d5ujjdfo.cloudfront.net/Api/Images/132745068931130966.jpg",
            "url": "https://dy0t2d5ujjdfo.cloudfront.net/#/activity-list/52"
        },
        "102": {
            "title": "麗克特自煮料理神器",
            "image": "http://dy0t2d5ujjdfo.cloudfront.net/Api/Images/132745068365339419.jpg",
            "url": "https://dy0t2d5ujjdfo.cloudfront.net/#/activity-list/47"
        },
        "101": {
            "title": "在家吃早餐",
            "image": "http://dy0t2d5ujjdfo.cloudfront.net/Api/Images/132745067879801499.jpg",
            "url": "https://dy0t2d5ujjdfo.cloudfront.net/#/activity-list/46"
        },
        "100": {
            "title": "中秋烤肉月預購",
            "image": "http://dy0t2d5ujjdfo.cloudfront.net/Api/Images/132745067339070040.jpg",
            "url": "https://dy0t2d5ujjdfo.cloudfront.net/#/activity-list/49"
        },
        "99": {
            "title": "中秋烤肉月",
            "image": "http://dy0t2d5ujjdfo.cloudfront.net/Api/Images/132745066149656897.jpg",
            "url": "https://dy0t2d5ujjdfo.cloudfront.net/#/activity-list/51"
        },
        "81": {
            "title": "朝市咖啡",
            "image": "http://dy0t2d5ujjdfo.cloudfront.net/Api/Images/14391.jpg",
            "url": "http://event.pxmart.com.tw/offcoffee/?ladosidg=26834&icmpid=AD006"
        }
    },
    "categories": {
        "3119": {
            "name": "本檔必買",
            "date": "2021/9/3-9/10"
        },
        "3123": {
            "name": "抗漲專區",
            "date": "2021/8/27-9/10"
        },
        "3144": {
            "name": "扣點買一送一",
            "date": "2021/8/27-9/10"
        },
        "3157": {
            "name": "卡友特惠價",
            "date": "2021/8/27-9/10"
        },
        "3177": {
            "name": "在家吃早餐",
            "date": "2021/8/27-9/10"
        },
        "3191": {
            "name": "中秋烤肉月",
            "date": "2021/8/27-9/10"
        },
        "3205": {
            "name": "露營外宿",
            "date": "2021/8/27-9/10"
        },
        "3212": {
            "name": "休閒食品、泡麵、麵製品",
            "date": "2021/8/27-9/10"
        },
        "3218": {
            "name": "冷藏、冰凍食品",
            "date": "2021/8/27-9/10"
        },
        "3224": {
            "name": "個人清潔與美妝、保健用品",
            "date": "2021/8/27-9/10"
        },
        "3226": {
            "name": "家用清潔品、五金耗材",
            "date": "2021/8/27-9/10"
        },
        "3229": {
            "name": "家用紙品、衛生棉",
            "date": "2021/8/27-9/10"
        },
        "3232": {
            "name": "嬰童/寵物、紡織品",
            "date": "2021/8/27-9/10"
        },
        "3237": {
            "name": "沖調營養品、保健食品",
            "date": "2021/8/27-9/10"
        },
        "3241": {
            "name": "南北貨、油品、調味料、罐頭",
            "date": "2021/8/27-9/10"
        },
        "3246": {
            "name": "飲料與酒類",
            "date": "2021/8/27-9/10"
        },
        "3249": {
            "name": "超級品牌月-佳格+佳乳",
            "date": "2021/8/27-9/10"
        },
        "3261": {
            "name": "超級品牌月-白蘭氏",
            "date": "2021/8/27-9/10"
        },
        "3263": {
            "name": "超級品牌月-太古",
            "date": "2021/8/27-9/10"
        },
        "3265": {
            "name": "超級品牌月-嬌聯",
            "date": "2021/8/27-9/10"
        },
        "3269": {
            "name": "超級品牌月-聯合利華",
            "date": "2021/8/27-9/10"
        },
        "3273": {
            "name": "超級品牌月-新竹物流-舒酸定/輝瑞",
            "date": "2021/8/27-9/10"
        }
    },
    "personas": {
        "newUser": {
            "name": "初次訪客 (New User)",
            "keywords": [
                "中秋節",
                "咖啡",
                "印花",
                "預購"
            ],
            "banners": [
                "103",
                "100",
                "99",
                "81",
                "102",
                "101"
            ],
            "categories": [
                "3157",
                "3119",
                "3191",
                "3123",
                "3177",
                "3144",
                "3205",
                "3212"
            ],
            "cookbooks": [
                33409,
                31426,
                484,
                268,
                5141,
                5140
            ]
        },
        "housekeeper": {
            "name": "家庭主婦",
            "keywords": [
                "中秋節",
                "衛生紙",
                "印花",
                "預購"
            ],
            "banners": [
                "103",
                "100",
                "99",
                "102",
                "101",
                "81"
            ],
            "categories": [
                "3144",
                "3123",
                "3226",
                "3157",
                "3269",
                "3191",
                "3205",
                "3212"
            ],
            "cookbooks": [
                2047,
                31849,
                29041,
                5119,
                2043,
                33542
            ]
        },
        "healthyPerson": {
            "name": "健康飲食愛好者",
            "keywords": [
                "素食",
                "養生",
                "有機",
                "中秋節"
            ],
            "banners": [
                "102",
                "101",
                "81",
                "103",
                "100",
                "99"
            ],
            "categories": [
                "3224",
                "3261",
                "3237",
                "3177",
                "3191",
                "3144",
                "3205",
                "3212"
            ],
            "cookbooks": [
                2046,
                1829,
                1849,
                1848,
                3071,
                33394
            ]
        },
        "officeWorker": {
            "name": "上班族",
            "keywords": [
                "紅酒",
                "中秋節",
                "咖啡",
                "預購"
            ],
            "banners": [
                "100",
                "99",
                "101",
                "81",
                "102",
                "103"
            ],
            "categories": [
                "3191",
                "3177",
                "3263",
                "3246",
                "3123",
                "3157",
                "3205",
                "3212"
            ],
            "cookbooks": [
                556,
                30995,
                31336,
                3085,
                1743,
                28923
            ]
        },
        "student": {
            "name": "學生",
            "keywords": [
                "咖啡",
                "中秋節",
                "金牌",
                "啤酒"
            ],
            "banners": [
                "81",
                "103",
                "99",
                "100",
                "101",
                "102"
            ],
            "categories": [
                "3123",
                "3191",
                "3246",
                "3263",
                "3144",
                "3157",
                "3205",
                "3212"
            ],
            "cookbooks": [
                4110,
                571,
                4118,
                4116,
                4109,
                4106
            ]
        }
    }
}